spy_ai/__init__.py
spy_ai-1.1.1.dist-info/METADATA
spy_ai-1.1.1.dist-info/WHEEL
spy_ai-1.1.1.dist-info/top_level.txt
spy_ai-1.1.1.dist-info/RECORD
