Metadata-Version: 2.1
Name: spy-ai
Version: 1.1.1
Summary: pip for AI now
Home-page: https://github.com/loverelyas/spider-ai
Author: spiderXR
Author-email: mostshariblis@gmail.com
Classifier: Programming Language :: Python :: 3
Classifier: License :: OSI Approved :: MIT License
Classifier: Operating System :: OS Independent
Requires-Python: >=3.6
